titerplot/__init__.py
titerplot/plotting.py
titerplot-0.1.0.dist-info/LICENSE
titerplot-0.1.0.dist-info/METADATA
titerplot-0.1.0.dist-info/WHEEL
titerplot-0.1.0.dist-info/RECORD
