Metadata-Version: 2.3
Name: titerplot
Version: 0.1.0
Summary: A Python package for plotting titer data with factorial/combinatorial designs.
Author: WillHannon-MCB
Author-email: hannonww@gmail.com
Requires-Python: >=3.12
Classifier: Programming Language :: Python :: 3
Classifier: License :: OSI Approved :: MIT License
Classifier: Operating System :: OS Independent
Requires-Dist: altair (>=5.5.0,<6.0.0)
Requires-Dist: pandas (>=2.2.3,<3.0.0)
Project-URL: Bug Tracker, https://github.com/WillHannon-MCB/titerplot/issues
Project-URL: Homepage, https://github.com/WillHannon-MCB/titerplot
